dumbo_asp/__init__.py
dumbo_asp/primitives/__init__.py
dumbo_asp/primitives/atoms.py
dumbo_asp/primitives/models.py
dumbo_asp/primitives/parsers.py
dumbo_asp/primitives/predicates.py
dumbo_asp/primitives/programs.py
dumbo_asp/primitives/rules.py
dumbo_asp/primitives/templates.py
dumbo_asp/primitives/terms.py
dumbo_asp/queries.py
dumbo_asp/templates/binary_relations.template.asp
dumbo_asp/templates/dumbo.template.asp
dumbo_asp/templates/graphs.template.asp
dumbo_asp/templates/grids.template.asp
dumbo_asp/templates/sets.template.asp
dumbo_asp/utils.py
dumbo_asp-0.3.17.dist-info/METADATA
dumbo_asp-0.3.17.dist-info/WHEEL
dumbo_asp-0.3.17.dist-info/licenses/LICENSE
dumbo_asp-0.3.17.dist-info/RECORD
