Metadata-Version: 2.4
Name: dumbo-asp
Version: 0.3.17
Summary: Utilities for Answer Set Programming
License-File: LICENSE
Author: Mario Alviano
Author-email: mario.alviano@gmail.com
Requires-Python: >=3.11,<4.0
Classifier: Programming Language :: Python :: 3
Classifier: Programming Language :: Python :: 3.11
Classifier: Programming Language :: Python :: 3.12
Classifier: Programming Language :: Python :: 3.13
Classifier: Programming Language :: Python :: 3.14
Requires-Dist: Pillow (>=10.3.0,<11.0.0)
Requires-Dist: cairocffi (>=1.7.1,<2.0.0)
Requires-Dist: click (<8.2.0)
Requires-Dist: clingo (>=5.8.0,<6.0.0)
Requires-Dist: clingox (>=1.2.1,<2.0.0)
Requires-Dist: dateutils (>=0.6.12,<0.7.0)
Requires-Dist: distlib (>=0.3.9,<0.4.0)
Requires-Dist: dumbo-utils (>=0.3.6,<0.4.0)
Requires-Dist: igraph (>=0.11.8,<0.12.0)
